TrackHand/trackhand.py
trackhand-2.0.dist-info/METADATA
trackhand-2.0.dist-info/WHEEL
trackhand-2.0.dist-info/top_level.txt
trackhand-2.0.dist-info/RECORD
