Metadata-Version: 2.1
Name: trackhand
Version: 2.0
Summary: This is a simple Hand tracking module
Home-page: UNKNOWN
Author: Sudhanshu Yadav
Author-email: sudhanshuy17@gmail.com
License: UNKNOWN
Platform: UNKNOWN
Requires-Dist: opencv-python
Requires-Dist: mediapipe
